README.txt
setup.py
quaternionarray/__init__.py
quaternionarray/test_quaternionarray.py
quaternionarray.egg-info/PKG-INFO
quaternionarray.egg-info/SOURCES.txt
quaternionarray.egg-info/dependency_links.txt
quaternionarray.egg-info/top_level.txt