Metadata-Version: 1.1
Name: quaternionarray
Version: 0.6.2
Summary: Python package for fast quaternion arrays math
Home-page: http://github.com/zonca/quaternionarray/
Author: Andrea Zonca
Author-email: code@andreazonca.com
License: GPL3
Keywords: quaternion,nlerp,rotate
Platform: UNKNOWN
Classifier: Development Status :: 3 - Alpha
Classifier: Environment :: Console
Classifier: Intended Audience :: Developers
Classifier: Intended Audience :: Science/Research
Classifier: License :: OSI Approved :: GNU General Public License (GPL)
Classifier: Operating System :: MacOS :: MacOS X
Classifier: Operating System :: Microsoft :: Windows
Classifier: Operating System :: POSIX
Classifier: Programming Language :: Python
Classifier: Topic :: Office/Business
Classifier: Topic :: Scientific/Engineering :: Physics
